MANIFEST.in
README.rst
setup.py
siht/__init__.py
siht.egg-info/PKG-INFO
siht.egg-info/SOURCES.txt
siht.egg-info/dependency_links.txt
siht.egg-info/top_level.txt
siht.egg-info/zip-safe