Metadata-Version: 1.1
Name: siht
Version: 0.1.2
Summary: An anti-explicit manifesto
Home-page: https://github.com/jpscaletti/siht
Author: Juan-Pablo Scaletti
Author-email: juanpablo@lucumalabs.com
License: MIT license
Platform: UNKNOWN
Classifier: Development Status :: 4 - Beta
Classifier: Intended Audience :: Developers
Classifier: License :: OSI Approved :: MIT License
Classifier: Operating System :: OS Independent
Classifier: Programming Language :: Python
Classifier: Programming Language :: Python :: 2
Classifier: Programming Language :: Python :: 3
Classifier: Topic :: Software Development :: Libraries :: Python Modules
